{"is_source_file": true, "format": "JavaScript (React JSX)", "description": "Source file for the main React application component of a Tic Tac Toe web app, responsible for rendering the app's layout, theme toggle button, and including the game component.", "external_files": ["./App.css", "./TicTacToeGame"], "external_methods": ["React.useState", "React.useEffect"], "published": ["default"], "classes": [], "methods": [{"name": "App()", "description": "Main React functional component that manages theme state and renders the app layout.", "scope": "", "scopeKind": ""}, {"name": "toggleTheme", "description": "Function to toggle between light and dark themes."}], "calls": ["React.useState", "React.useEffect", "document.documentElement.setAttribute", "setTheme", "toggleTheme"], "search-terms": ["React functional component", "theme toggle", "TicTacToeGame inclusion", "App layout", "React hooks"], "state": 2, "file_id": 8, "knowledge_revision": 28, "git_revision": "5fd23686dcc71f02ecf6620cced1e4280bd09bfe", "revision_history": [{"20": "5fd23686dcc71f02ecf6620cced1e4280bd09bfe"}, {"28": "5fd23686dcc71f02ecf6620cced1e4280bd09bfe"}], "ctags": [{"_type": "tag", "name": "App", "path": "/home/kavia/workspace/code-generation/tic-tac-toe-web-app-dffd920e/tic_tac_toe_frontend/src/App.js", "pattern": "/^function App() {$/", "language": "JavaScript", "kind": "function", "signature": "()"}, {"_type": "tag", "name": "Switch to ${theme === \"light\" ? \"dark\" : \"light\"} mode", "path": "/home/kavia/workspace/code-generation/tic-tac-toe-web-app-dffd920e/tic_tac_toe_frontend/src/App.js", "pattern": "/^          aria-label={`Switch to ${theme === \"light\" ? \"dark\" : \"light\"} mode`}$/", "language": "JavaScript", "kind": "field", "scope": "aria", "scopeKind": "class"}, {"_type": "tag", "name": "toggleTheme", "path": "/home/kavia/workspace/code-generation/tic-tac-toe-web-app-dffd920e/tic_tac_toe_frontend/src/App.js", "pattern": "/^          onClick={toggleTheme}$/", "language": "JavaScript", "kind": "field", "scope": "App.onClick", "scopeKind": "class"}], "hash": "62551507c1b0da3fcc3cc1f80cf8fb23", "format-version": 4, "code-base-name": "tic_tac_toe_frontend", "filename": "tic_tac_toe_frontend/src/App.js", "fields": [{"name": "aria-label={`Switch to ${theme === \"light\" ? \"dark\" : \"light\"} mode`}", "scope": "aria", "scopeKind": "class", "description": "unavailable"}, {"name": "onClick={toggleTheme}", "scope": "App.onClick", "scopeKind": "class", "description": "unavailable"}]}